html2csv/__init__.py
html2csv/__main__.py
html2csv/converter.py
html2csv/version.py
html_to_csv-0.1.3.dist-info/LICENSE
html_to_csv-0.1.3.dist-info/METADATA
html_to_csv-0.1.3.dist-info/WHEEL
html_to_csv-0.1.3.dist-info/entry_points.txt
html_to_csv-0.1.3.dist-info/top_level.txt
html_to_csv-0.1.3.dist-info/RECORD
