Metadata-Version: 2.1
Name: html-to-csv
Version: 0.1.3
Summary: A utility that extracts tables from HTML documents and converts them to CSV format
Home-page: https://github.com/hanwentao/html2csv
Author: Wentao Han
Author-email: wentao.han@gmail.com
License: UNKNOWN
Keywords: html table csv convert
Platform: UNKNOWN
Classifier: Development Status :: 3 - Alpha
Classifier: Operating System :: OS Independent
Classifier: License :: OSI Approved :: MIT License
Classifier: Programming Language :: Python :: 3
Classifier: Programming Language :: Python :: 3.6
Classifier: Programming Language :: Python :: 3.7
Requires-Python: >=3.6, <4
Provides-Extra: test
Provides-Extra: dev
